chromcocluster/__init__.py
chromcocluster/accessibility_matrix.py
chromcocluster/cocluster.py
chromcocluster/locus_cluster.py
chromcocluster/null_locus_cluster.py
chromcocluster/optimize_tree_cluster.py
chromcocluster/tree_cluster.py
chromcocluster/utilities.py
chromcocluster-0.0.5.dist-info/LICENSE
chromcocluster-0.0.5.dist-info/METADATA
chromcocluster-0.0.5.dist-info/WHEEL
chromcocluster-0.0.5.dist-info/top_level.txt
chromcocluster-0.0.5.dist-info/RECORD
