Metadata-Version: 2.1
Name: chromcocluster
Version: 0.0.5
Summary: Co-clustering of chromatin accessibility data across cell types
Home-page: https://github.com/SLeviyang/chromcocluster
Author: Thomas George and Sivan Leviyang
Author-email: Sivan.Leviyang@georgetown.edu
License: UNKNOWN
Project-URL: Bug Tracker, https://github.com/SLeviyang/chromcocluster/issues
Platform: UNKNOWN
Classifier: Programming Language :: Python :: 3
Classifier: License :: OSI Approved :: MIT License
Classifier: Operating System :: OS Independent
Requires-Python: >=3.6
License-File: LICENSE
